Metadata-Version: 1.1
Name: utknows
Version: 0.1.1
Summary: UNKNOWN
Home-page: http://mapix.me/utknows/
Author: mapix
Author-email: mapix.me@gmail.com
License: BSD
Platform: UNKNOWN
Classifier: License :: OSI Approved :: BSD License
